friendlydb/__init__.py
friendlydb/db.py
friendlydb/server.py
friendlydb/user.py
friendlydb-2.0.0.dist-info/DESCRIPTION.rst
friendlydb-2.0.0.dist-info/METADATA
friendlydb-2.0.0.dist-info/pydist.json
friendlydb-2.0.0.dist-info/RECORD
friendlydb-2.0.0.dist-info/top_level.txt
friendlydb-2.0.0.dist-info/WHEEL
