Metadata-Version: 2.0
Name: friendlydb
Version: 2.0.0
Summary: A small & fast following/followers database.
Home-page: http://github.com/toastdriven/friendlydb
Author: Daniel Lindsley
Author-email: daniel@toastdriven.com
License: UNKNOWN
Platform: UNKNOWN
Classifier: Development Status :: 5 - Stable
Classifier: Intended Audience :: Developers
Classifier: License :: OSI Approved :: BSD License
Classifier: Operating System :: OS Independent
Classifier: Programming Language :: Python
Classifier: Programming Language :: Python :: 3
Requires-Dist: redis (>=2.72)
